cytoscnpy/__init__.py
cytoscnpy/__main__.py
cytoscnpy/cli.py
cytoscnpy/cytoscnpy.cpython-312-darwin.so
cytoscnpy-1.2.10.dist-info/METADATA
cytoscnpy-1.2.10.dist-info/WHEEL
cytoscnpy-1.2.10.dist-info/entry_points.txt
cytoscnpy-1.2.10.dist-info/RECORD
