Metadata-Version: 2.4
Name: cytoscnpy
Version: 1.2.10
Classifier: Programming Language :: Rust
Classifier: Programming Language :: Python :: 3
Classifier: Programming Language :: Python :: 3.8
Classifier: Programming Language :: Python :: 3.9
Classifier: Programming Language :: Python :: 3.10
Classifier: Programming Language :: Python :: 3.11
Classifier: Programming Language :: Python :: 3.12
Classifier: Programming Language :: Python :: 3.13
Classifier: Programming Language :: Python :: Implementation :: CPython
Classifier: Programming Language :: Python :: Implementation :: PyPy
Classifier: Topic :: Software Development :: Quality Assurance
Classifier: Topic :: Software Development :: Testing
Classifier: Intended Audience :: Developers
Classifier: License :: OSI Approved :: Apache Software License
Classifier: Operating System :: OS Independent
Requires-Dist: prek ; extra == 'dev'
Requires-Dist: psutil ; extra == 'dev'
Requires-Dist: pytest>=7.0 ; extra == 'dev'
Requires-Dist: pytest-cov>=4.0 ; extra == 'dev'
Requires-Dist: ruff ; extra == 'dev'
Requires-Dist: tomli ; python_full_version < '3.11' and extra == 'dev'
Requires-Dist: trove-classifiers ; extra == 'dev'
Requires-Dist: ty ; extra == 'dev'
Requires-Dist: mkdocs-material>=9.5.0 ; python_full_version >= '3.9' and extra == 'docs'
Requires-Dist: mkdocs-minify-plugin>=0.8.0 ; python_full_version >= '3.9' and extra == 'docs'
Requires-Dist: pymdown-extensions>=10.0 ; python_full_version >= '3.9' and extra == 'docs'
Provides-Extra: dev
Provides-Extra: docs
Summary: High-performance dead code elimination analysis tool for Python.
Requires-Python: >=3.8
